doc/ioutils.md
narf/ioutils.py
narf_ioutils-0.1.7.dist-info/METADATA
narf_ioutils-0.1.7.dist-info/WHEEL
narf_ioutils-0.1.7.dist-info/top_level.txt
narf_ioutils-0.1.7.dist-info/RECORD
